verilog/PE.v
module PE (
    // input              IN_valid, 
    input              STDW, // == 1 if standard write mode (weight updating)
    input              STDR, // == 1 if standard read mode
    input        [5:0] STD_A, // address for determining which row (1 out of 64) to read/write
    input        [3:0] weight_in, // update 4b weight when STDW
    // input              CIM_A,
    input      [255:0] act_in, // 4b x 64
    output reg   [3:0] weight_out, // read out 4b weight when STDR
    output reg  [13:0] PSUM // 14b output
);

// regs and wires
// reg  [7:0] mult_res [0:63];
reg  [3:0] weight   [0:63];

integer i;


always@(*) begin
    weight_out = 4'b0;
    PSUM = 14'b0;
    if (STDW) begin // weight update
        weight[STD_A] = weight_in;
    end
    else if (STDR) begin // read out weight
        weight_out = weight[STD_A];
    end
    else begin // normal CIM operation
        for (i = 0; i < 64; i = i+1) begin
            PSUM = PSUM + weight[i] * act_in[4*i+3 -: 4]; // 4b input activation
        end
    end
end

    
endmodule

verilog/PE_tb.v
`timescale 1ns/10ps
`define CYCLE 10.0

module PE_tb;

// clk generation
reg clk = 1;
always #(`CYCLE/2) clk = ~clk;


// dump waveform
// vcd
initial begin
    $dumpfile("PE.vcd");
    $dumpvars(0, pe0);
end
// fsdb
// initial begin
//     $fsdbDumpfile("PE.fsdb");
//     $fsdbDumpvars(0, "+mda");
// end

// time out
initial begin
    # (10000 * `CYCLE);
    $display("\n\033[1;31m=============================================");
	$display("           Simulation Time Out!      ");
	$display("=============================================\033[0m");
	$finish;
end

// instantiate DUT
reg          STDW = 0, STDR = 0;
reg    [5:0] STD_A = 0;
reg    [3:0] weight_in = 0;
reg  [255:0] act_in = 0;
wire   [3:0] weight_out;
wire [13:0] PSUM;

PE pe0(
    .STDW(STDW),
    .STDR(STDR),
    .STD_A(STD_A),
    .weight_in(weight_in), // 4b
    .act_in(act_in), // 4b x 64
    .weight_out(weight_out),
    .PSUM(PSUM) // 14b output
);

// input pattern
integer i;

initial begin
    // update weight
    @(posedge clk) STDW = 1;
    @(posedge clk)
    for (i = 0; i < 64; i = i+1) begin
        STD_A = STD_A + 1;
        weight_in = weight_in + 1;
        @(posedge clk);
    end
    @(posedge clk)
    STDW = 0;
    STDR = 1;
    STD_A = 35;
    @(posedge clk)
    STDW = 0;
    STDR = 0;
    act_in = 256'b1111111111111111111111111111111111111111111111111111111111111111111111111111111111111111111111111111111111111111111111111111111111111111111111111111111111111111111111111111111111111111111111111111111111111111111111111111111111111111111111111111111111111111;
end

endmodule

verilog/PE.vcd
$date
	Fri Apr 29 16:15:10 2022
$end
$version
	Icarus Verilog
$end
$timescale
	10ps
$end
$scope module PE_tb $end
$scope module pe0 $end
$var wire 1 ! STDR $end
$var wire 1 " STDW $end
$var wire 6 # STD_A [5:0] $end
$var wire 256 $ act_in [255:0] $end
$var wire 4 % weight_in [3:0] $end
$var reg 14 & PSUM [13:0] $end
$var reg 4 ' weight_out [3:0] $end
$var integer 32 ( i [31:0] $end
$upscope $end
$upscope $end
$enddefinitions $end
#0
$dumpvars
b1000000 (
b0 '
bx &
b0 %
b0 $
b0 #
0"
0!
$end
#1000
b0 &
1"
#2000
b1 %
b1 #
#3000
b10 %
b10 #
#4000
b11 %
b11 #
#5000
b100 %
b100 #
#6000
b101 %
b101 #
#7000
b110 %
b110 #
#8000
b111 %
b111 #
#9000
b1000 %
b1000 #
#10000
b1001 %
b1001 #
#11000
b1010 %
b1010 #
#12000
b1011 %
b1011 #
#13000
b1100 %
b1100 #
#14000
b1101 %
b1101 #
#15000
b1110 %
b1110 #
#16000
b1111 %
b1111 #
#17000
b0 %
b10000 #
#18000
b1 %
b10001 #
#19000
b10 %
b10010 #
#20000
b11 %
b10011 #
#21000
b100 %
b10100 #
#22000
b101 %
b10101 #
#23000
b110 %
b10110 #
#24000
b111 %
b10111 #
#25000
b1000 %
b11000 #
#26000
b1001 %
b11001 #
#27000
b1010 %
b11010 #
#28000
b1011 %
b11011 #
#29000
b1100 %
b11100 #
#30000
b1101 %
b11101 #
#31000
b1110 %
b11110 #
#32000
b1111 %
b11111 #
#33000
b0 %
b100000 #
#34000
b1 %
b100001 #
#35000
b10 %
b100010 #
#36000
b11 %
b100011 #
#37000
b100 %
b100100 #
#38000
b101 %
b100101 #
#39000
b110 %
b100110 #
#40000
b111 %
b100111 #
#41000
b1000 %
b101000 #
#42000
b1001 %
b101001 #
#43000
b1010 %
b101010 #
#44000
b1011 %
b101011 #
#45000
b1100 %
b101100 #
#46000
b1101 %
b101101 #
#47000
b1110 %
b101110 #
#48000
b1111 %
b101111 #
#49000
b0 %
b110000 #
#50000
b1 %
b110001 #
#51000
b10 %
b110010 #
#52000
b11 %
b110011 #
#53000
b100 %
b110100 #
#54000
b101 %
b110101 #
#55000
b110 %
b110110 #
#56000
b111 %
b110111 #
#57000
b1000 %
b111000 #
#58000
b1001 %
b111001 #
#59000
b1010 %
b111010 #
#60000
b1011 %
b111011 #
#61000
b1100 %
b111100 #
#62000
b1101 %
b111101 #
#63000
b1110 %
b111110 #
#64000
b1111 %
b111111 #
#65000
b0 %
b0 #
#67000
b11 '
b100011 #
1!
0"
#68000
b1110000100000 &
b1000000 (
b0 '
b1111111111111111111111111111111111111111111111111111111111111111111111111111111111111111111111111111111111111111111111111111111111111111111111111111111111111111111111111111111111111111111111111111111111111111111111111111111111111111111111111111111111111111 $
0!
